README.md
setup.py
esp/__init__.py
esp/esp.py
esp/gp_utils.py
esp/pca.py
esp/plot_utils.py
esp/spec_utils.py
esp/lsst_utils/Bandpass.py
esp/lsst_utils/BandpassDict.py
esp/lsst_utils/PhysicalParameters.py
esp/lsst_utils/Sed.py
esp/lsst_utils/__init__.py
esphot.egg-info/PKG-INFO
esphot.egg-info/SOURCES.txt
esphot.egg-info/dependency_links.txt
esphot.egg-info/requires.txt
esphot.egg-info/top_level.txt