Metadata-Version: 1.1
Name: esphot
Version: 0.4.0
Summary: Estimating Spectra from Photometry
Home-page: https://github.com/jbkalmbach/esp
Author: Bryce Kalmbach
Author-email: brycek@uw.edu
License: UNKNOWN
Platform: UNKNOWN
Classifier: Development Status :: 3 - Alpha
Classifier: License :: OSI Approved :: GNU General Public License v3 (GPLv3)
Classifier: Intended Audience :: Science/Research
Classifier: Operating System :: OS Independent
Classifier: Programming Language :: Python
